[{"id":224, "speed":0.096, "density":0.22}, {"id":268, "speed":0.082, "density":0.16125}, {"id":500, "speed":0.077, "density":0.15375}, {"id":73, "speed":0.089, "density":0.21625}, {"id":139, "speed":0.089, "density":0.22375}, {"id":288, "speed":0.075, "density":0.15625}, {"id":94, "speed":0.074, "density":0.15375}, {"id":172, "speed":0.074, "density":0.15375}, {"id":209, "speed":0.087, "density":0.22625}, {"id":167, "speed":0.073, "density":0.165}, {"id":233, "speed":0.072, "density":0.16125}, {"id":63, "speed":0.066, "density":0.17125}, {"id":275, "speed":0.066, "density":0.17}, {"id":256, "speed":0.067, "density":0.17375}, {"id":389, "speed":0.09, "density":0.30625}, {"id":292, "speed":0.065, "density":0.17125}, {"id":307, "speed":0.068, "density":0.18375}, {"id":412, "speed":0.08, "density":0.3025}, {"id":490, "speed":0.09, "density":0.30625}, {"id":495, "speed":0.088, "density":0.29875}, {"id":29, "speed":0.066, "density":0.16875}, {"id":396, "speed":0.063, "density":0.16875}, {"id":95, "speed":0.076, "density":0.29}, {"id":440, "speed":0.076, "density":0.285}, {"id":105, "speed":0.062, "density":0.16375}, {"id":325, "speed":0.092, "density":0.30875}, {"id":67, "speed":0.088, "density":0.30875}, {"id":352, "speed":0.087, "density":0.30125}, {"id":399, "speed":0.09, "density":0.305}, {"id":442, "speed":0.085, "density":0.305}, {"id":74, "speed":0.086, "density":0.305}, {"id":338, "speed":0.089, "density":0.30125}, {"id":176, "speed":0.087, "density":0.30125}, {"id":151, "speed":0.084, "density":0.305}, {"id":484, "speed":0.089, "density":0.30625}, {"id":178, "speed":0.085, "density":0.29875}, {"id":13, "speed":0.088, "density":0.30375}, {"id":200, "speed":0.086, "density":0.305}, {"id":92, "speed":0.085, "density":0.30125}, {"id":152, "speed":0.088, "density":0.30875}, {"id":328, "speed":0.084, "density":0.34375}, {"id":149, "speed":0.083, "density":0.3425}, {"id":372, "speed":0.083, "density":0.345}, {"id":384, "speed":0.086, "density":0.3475}, {"id":413, "speed":0.082, "density":0.3475}, {"id":30, "speed":0.083, "density":0.34375}, {"id":463, "speed":0.083, "density":0.33875}, {"id":228, "speed":0.084, "density":0.34}, {"id":15, "speed":0.086, "density":0.33}, {"id":38, "speed":0.083, "density":0.335}, {"id":491, "speed":0.083, "density":0.335}, {"id":48, "speed":0.082, "density":0.33125}, {"id":254, "speed":0.082, "density":0.33625}, {"id":263, "speed":0.082, "density":0.33375}, {"id":266, "speed":0.083, "density":0.33125}, {"id":309, "speed":0.083, "density":0.325}, {"id":273, "speed":0.083, "density":0.32375}, {"id":317, "speed":0.084, "density":0.3175}, {"id":382, "speed":0.081, "density":0.3225}, {"id":374, "speed":0.083, "density":0.31125}, {"id":385, "speed":0.083, "density":0.30375}, {"id":157, "speed":0.079, "density":0.28375}, {"id":358, "speed":0.077, "density":0.27625}, {"id":496, "speed":0.081, "density":0.295}, {"id":81, "speed":0.077, "density":0.27875}, {"id":6, "speed":0.08, "density":0.29}, {"id":40, "speed":0.077, "density":0.27625}, {"id":93, "speed":0.077, "density":0.27875}, {"id":68, "speed":0.079, "density":0.2925}, {"id":143, "speed":0.08, "density":0.29}, {"id":434, "speed":0.077, "density":0.2825}, {"id":215, "speed":0.076, "density":0.27875}, {"id":300, "speed":0.079, "density":0.29625}, {"id":316, "speed":0.076, "density":0.28375}, {"id":469, "speed":0.077, "density":0.28375}, {"id":137, "speed":0.077, "density":0.29375}, {"id":20, "speed":0.076, "density":0.295}, {"id":367, "speed":0.074, "density":0.27875}, {"id":454, "speed":0.079, "density":0.29375}, {"id":295, "speed":0.077, "density":0.2975}, {"id":312, "speed":0.078, "density":0.29375}, {"id":418, "speed":0.073, "density":0.28125}, {"id":478, "speed":0.075, "density":0.2925}, {"id":321, "speed":0.076, "density":0.295}, {"id":395, "speed":0.076, "density":0.3}, {"id":17, "speed":0.092, "density":0.2925}, {"id":89, "speed":0.089, "density":0.285}, {"id":77, "speed":0.093, "density":0.29375}, {"id":193, "speed":0.089, "density":0.29}, {"id":348, "speed":0.092, "density":0.28625}, {"id":159, "speed":0.088, "density":0.2875}, {"id":407, "speed":0.088, "density":0.2925}, {"id":482, "speed":0.093, "density":0.2875}, {"id":16, "speed":0.087, "density":0.28625}, {"id":19, "speed":0.089, "density":0.28875}, {"id":54, "speed":0.088, "density":0.28625}, {"id":39, "speed":0.092, "density":0.28375}, {"id":78, "speed":0.088, "density":0.27375}, {"id":108, "speed":0.087, "density":0.27375}, {"id":171, "speed":0.087, "density":0.28125}, {"id":25, "speed":0.004, "density":0.30375}, {"id":62, "speed":0.004, "density":0.29875}, {"id":397, "speed":0.004, "density":0.29375}, {"id":113, "speed":0.004, "density":0.28625}, {"id":433, "speed":0.004, "density":0.29}, {"id":177, "speed":0.004, "density":0.30125}, {"id":467, "speed":0.004, "density":0.2875}, {"id":164, "speed":0.004, "density":0.285}, {"id":186, "speed":0.004, "density":0.29125}, {"id":31, "speed":0.004, "density":0.2825}, {"id":267, "speed":0.004, "density":0.2875}, {"id":181, "speed":0.004, "density":0.28625}, {"id":290, "speed":0.004, "density":0.2875}, {"id":339, "speed":0.004, "density":0.28375}, {"id":191, "speed":0.004, "density":0.28375}, {"id":417, "speed":0.004, "density":0.2775}, {"id":445, "speed":0.004, "density":0.2825}, {"id":251, "speed":0.004, "density":0.28}, {"id":117, "speed":0.004, "density":0.28625}, {"id":379, "speed":0.004, "density":0.2775}, {"id":237, "speed":0.004, "density":0.28375}, {"id":86, "speed":0.004, "density":0.29}, {"id":293, "speed":0.004, "density":0.27875}, {"id":147, "speed":0.004, "density":0.28875}, {"id":378, "speed":0.004, "density":0.28375}, {"id":400, "speed":0.004, "density":0.27875}, {"id":426, "speed":0.004, "density":0.28}, {"id":350, "speed":0.004, "density":0.27625}, {"id":410, "speed":0.004, "density":0.27875}, {"id":458, "speed":0.004, "density":0.2825}, {"id":492, "speed":0.004, "density":0.2875}, {"id":2, "speed":0.004, "density":0.2975}, {"id":37, "speed":0.004, "density":0.2825}, {"id":179, "speed":0.004, "density":0.29375}, {"id":202, "speed":0.004, "density":0.2975}, {"id":326, "speed":0.004, "density":0.3}, {"id":214, "speed":0.004, "density":0.29875}, {"id":315, "speed":0.004, "density":0.3}, {"id":349, "speed":0.004, "density":0.3}, {"id":225, "speed":0.004, "density":0.29875}, {"id":439, "speed":0.004, "density":0.3025}, {"id":145, "speed":0.004, "density":0.32875}, {"id":345, "speed":0.004, "density":0.33125}, {"id":201, "speed":0.004, "density":0.33}, {"id":360, "speed":0.004, "density":0.32875}, {"id":61, "speed":0.004, "density":0.33}, {"id":461, "speed":0.004, "density":0.33}, {"id":124, "speed":0.004, "density":0.33}, {"id":211, "speed":0.004, "density":0.33125}, {"id":250, "speed":0.004, "density":0.33375}, {"id":308, "speed":0.004, "density":0.33}, {"id":223, "speed":0.004, "density":0.32875}, {"id":320, "speed":0.004, "density":0.33125}, {"id":329, "speed":0.004, "density":0.33125}, {"id":381, "speed":0.004, "density":0.32625}, {"id":330, "speed":0.004, "density":0.33125}, {"id":10, "speed":0.004, "density":0.315}, {"id":160, "speed":0.004, "density":0.315}, {"id":8, "speed":0.004, "density":0.315}, {"id":12, "speed":0.004, "density":0.32375}, {"id":245, "speed":0.004, "density":0.31125}, {"id":97, "speed":0.004, "density":0.31125}, {"id":104, "speed":0.004, "density":0.31}, {"id":187, "speed":0.004, "density":0.305}, {"id":248, "speed":0.004, "density":0.305}, {"id":244, "speed":0.004, "density":0.305}, {"id":493, "speed":0.004, "density":0.305}, {"id":4, "speed":0.004, "density":0.30375}, {"id":76, "speed":0.004, "density":0.3}, {"id":98, "speed":0.004, "density":0.2925}, {"id":47, "speed":0.004, "density":0.28625}, {"id":285, "speed":0.004, "density":0.28625}, {"id":82, "speed":0.004, "density":0.28875}, {"id":84, "speed":0.004, "density":0.2775}, {"id":475, "speed":0.004, "density":0.2775}, {"id":231, "speed":0.004, "density":0.2775}, {"id":271, "speed":0.004, "density":0.27875}, {"id":323, "speed":0.004, "density":0.26625}, {"id":408, "speed":0.004, "density":0.2675}, {"id":450, "speed":0.004, "density":0.27}, {"id":438, "speed":0.004, "density":0.265}, {"id":459, "speed":0.004, "density":0.2675}, {"id":460, "speed":0.004, "density":0.26125}, {"id":102, "speed":0.004, "density":0.2625}, {"id":111, "speed":0.004, "density":0.2625}, {"id":156, "speed":0.004, "density":0.26125}, {"id":173, "speed":0.004, "density":0.26875}, {"id":241, "speed":0.004, "density":0.26875}, {"id":87, "speed":0.076, "density":0.30875}, {"id":53, "speed":0.074, "density":0.305}, {"id":322, "speed":0.075, "density":0.3125}, {"id":272, "speed":0.074, "density":0.31}, {"id":153, "speed":0.073, "density":0.305}, {"id":464, "speed":0.075, "density":0.30125}, {"id":234, "speed":0.072, "density":0.3}, {"id":246, "speed":0.071, "density":0.30125}, {"id":80, "speed":0.074, "density":0.295}, {"id":85, "speed":0.075, "density":0.2875}, {"id":287, "speed":0.072, "density":0.29875}, {"id":96, "speed":0.073, "density":0.28875}, {"id":311, "speed":0.071, "density":0.2925}, {"id":313, "speed":0.074, "density":0.28375}, {"id":57, "speed":0.074, "density":0.28375}, {"id":333, "speed":0.074, "density":0.28375}, {"id":347, "speed":0.07, "density":0.29875}, {"id":436, "speed":0.074, "density":0.27875}, {"id":447, "speed":0.071, "density":0.2875}, {"id":483, "speed":0.074, "density":0.27875}, {"id":377, "speed":0.069, "density":0.29}, {"id":487, "speed":0.069, "density":0.2925}, {"id":494, "speed":0.069, "density":0.2925}, {"id":141, "speed":0.073, "density":0.275}, {"id":1, "speed":0.07, "density":0.28125}, {"id":32, "speed":0.067, "density":0.2825}, {"id":210, "speed":0.07, "density":0.27625}, {"id":75, "speed":0.069, "density":0.27875}, {"id":230, "speed":0.072, "density":0.27375}, {"id":119, "speed":0.069, "density":0.29}, {"id":262, "speed":0.072, "density":0.27625}, {"id":264, "speed":0.072, "density":0.2775}, {"id":180, "speed":0.07, "density":0.2775}, {"id":344, "speed":0.069, "density":0.27875}, {"id":423, "speed":0.072, "density":0.28}, {"id":488, "speed":0.071, "density":0.27875}, {"id":116, "speed":0.072, "density":0.27875}, {"id":319, "speed":0.071, "density":0.3175}, {"id":301, "speed":0.07, "density":0.3175}, {"id":394, "speed":0.071, "density":0.3175}, {"id":24, "speed":0.067, "density":0.31}, {"id":343, "speed":0.071, "density":0.31625}, {"id":236, "speed":0.068, "density":0.32}, {"id":471, "speed":0.071, "density":0.315}, {"id":107, "speed":0.066, "density":0.3125}, {"id":281, "speed":0.068, "density":0.31375}, {"id":165, "speed":0.067, "density":0.31625}, {"id":135, "speed":0.066, "density":0.3175}, {"id":296, "speed":0.066, "density":0.31625}, {"id":452, "speed":0.068, "density":0.30875}, {"id":404, "speed":0.066, "density":0.3125}]